[{"id":1,"title":"Paradise","genres":"Romance","image":"http://dummyimage.com/114x100.png/dddddd/000000"},
{"id":2,"title":"Full Tilt Boogie","genres":"Documentary","image":"http://dummyimage.com/115x100.png/ff4444/ffffff"},
{"id":3,"title":"3 Women (Three Women)","genres":"Drama","image":"http://dummyimage.com/198x100.png/ff4444/ffffff"},
{"id":4,"title":"Nueba Yol","genres":"Comedy|Drama","image":"http://dummyimage.com/150x100.png/dddddd/000000"},
{"id":5,"title":"Cursed","genres":"Horror|Thriller","image":"http://dummyimage.com/180x100.png/dddddd/000000"},
{"id":6,"title":"Facing the Giants","genres":"Action|Drama","image":"http://dummyimage.com/116x100.png/5fa2dd/ffffff"},
{"id":7,"title":"Lake Mungo","genres":"Drama|Mystery|Thriller","image":"http://dummyimage.com/226x100.png/dddddd/000000"},
{"id":8,"title":"Sex Positive","genres":"Documentary","image":"http://dummyimage.com/188x100.png/dddddd/000000"},
{"id":9,"title":"Law, The (a.k.a. Where the Hot Wind Blows!) (Legge, La)","genres":"Drama","image":"http://dummyimage.com/163x100.png/cc0000/ffffff"},
{"id":10,"title":"Terumae romae (Thermae Romae)","genres":"Comedy|Sci-Fi","image":"http://dummyimage.com/141x100.png/cc0000/ffffff"},
{"id":11,"title":"My Life in Orange (Sommer in Orange)","genres":"Comedy","image":"http://dummyimage.com/205x100.png/cc0000/ffffff"},
{"id":12,"title":"Eve's Bayou","genres":"Drama","image":"http://dummyimage.com/190x100.png/dddddd/000000"},
{"id":13,"title":"Cab for Three, A (Taxi para tres)","genres":"Action|Comedy|Crime|Drama","image":"http://dummyimage.com/104x100.png/dddddd/000000"},
{"id":14,"title":"Initiation, The","genres":"Horror|Mystery|Thriller","image":"http://dummyimage.com/120x100.png/cc0000/ffffff"},
{"id":15,"title":"Story of Film: An Odyssey, The","genres":"Documentary","image":"http://dummyimage.com/156x100.png/cc0000/ffffff"},
{"id":16,"title":"Le grand soir","genres":"Comedy","image":"http://dummyimage.com/170x100.png/cc0000/ffffff"},
{"id":17,"title":"Hotel","genres":"Drama","image":"http://dummyimage.com/200x100.png/dddddd/000000"},
{"id":18,"title":"Beau Pere (a.k.a. Stepfather) (Beau-père)","genres":"Drama","image":"http://dummyimage.com/123x100.png/ff4444/ffffff"},
{"id":19,"title":"Teheran 43: Spy Ring (a.k.a. Assassination Attempt) (Tegeran-43)","genres":"Action|Crime|Drama|Thriller","image":"http://dummyimage.com/177x100.png/5fa2dd/ffffff"},
{"id":20,"title":"Mickey, Donald, Goofy: The Three Musketeers","genres":"Adventure|Animation|Children|Comedy","image":"http://dummyimage.com/167x100.png/cc0000/ffffff"},
{"id":21,"title":"Monsturd","genres":"Comedy|Horror","image":"http://dummyimage.com/185x100.png/5fa2dd/ffffff"},
{"id":22,"title":"Ice Princess","genres":"Children|Comedy|Drama","image":"http://dummyimage.com/200x100.png/dddddd/000000"},
{"id":23,"title":"Street Fighter: The Legend of Chun-Li","genres":"Action|Adventure|Sci-Fi|Thriller","image":"http://dummyimage.com/208x100.png/cc0000/ffffff"},
{"id":24,"title":"Kanal","genres":"Drama|War","image":"http://dummyimage.com/225x100.png/cc0000/ffffff"},
{"id":25,"title":"Katsastus","genres":"Comedy|Drama","image":"http://dummyimage.com/243x100.png/ff4444/ffffff"},
{"id":26,"title":"One Fine Day","genres":"Drama|Romance","image":"http://dummyimage.com/192x100.png/5fa2dd/ffffff"},
{"id":27,"title":"Lost Angels","genres":"Drama","image":"http://dummyimage.com/175x100.png/cc0000/ffffff"},
{"id":28,"title":"Puppet Master: Axis of Evil (Puppet Master 10)","genres":"Horror","image":"http://dummyimage.com/133x100.png/dddddd/000000"},
{"id":29,"title":"Outside the Law (Hors-la-loi)","genres":"Crime|Drama|War","image":"http://dummyimage.com/224x100.png/ff4444/ffffff"},
{"id":30,"title":"Analyze This","genres":"Comedy","image":"http://dummyimage.com/237x100.png/cc0000/ffffff"}]